{
"empty": [
  0, 0, 0, 0, 0, 0, 0,
  0, 0, 0, 0, 0, 0, 0,
  0, 0, 0, 0, 0, 0, 0,
  0, 0, 0, 0, 0, 0, 0,
  0, 0, 0, 0, 0, 0, 0,
  0, 0, 0, 0, 0, 0, 0,
  0, 0, 0, 0, 0, 0, 0],

"ac": [
  1, 1, 1, 1, 1, 1, 1,
  1, 0, 0, 0, 0, 0, 1,
  1, 1, 1, 1, 1, 1, 1,
  1, 0, 0, 0, 0, 0, 1,
  1, 0, 1, 1, 1, 0, 1,
  1, 0, 1, 0, 0, 0, 1,
  1, 0, 1, 1, 1, 0, 1],

"b": [
  1, 1, 1, 1, 1, 1, 1,
  1, 0, 0, 0, 0, 0, 1,
  1, 0, 0, 0, 0, 0, 1,
  1, 0, 0, 1, 1, 1, 0,
  1, 0, 0, 0, 0, 0, 1,
  1, 0, 0, 0, 0, 0, 1,
  1, 1, 1, 1, 1, 1, 1],

"cc": [
  1, 1, 1, 1, 1, 1, 1,
  1, 0, 0, 0, 0, 0, 0,
  1, 0, 1, 1, 1, 1, 1,
  1, 0, 1, 0, 0, 0, 0,
  1, 0, 1, 1, 1, 1, 1,
  1, 0, 0, 0, 0, 0, 0,
  1, 1, 1, 1, 1, 1, 1],

"cd": [
  1, 1, 1, 1, 1, 1, 1,
  1, 0, 0, 0, 0, 0, 0,
  1, 0, 0, 1, 1, 1, 0,
  1, 0, 1, 0, 0, 0, 1,
  1, 0, 1, 1, 1, 1, 1,
  1, 0, 0, 0, 0, 0, 0,
  1, 1, 1, 1, 1, 1, 1],

"cm": [
  1, 1, 1, 1, 1, 0, 0,
  0, 0, 0, 0, 1, 0, 0,
  1, 1, 1, 0, 1, 1, 1,
  1, 0, 0, 0, 0, 0, 1,
  1, 0, 0, 0, 0, 0, 1,
  1, 0, 0, 0, 0, 0, 1,
  1, 1, 1, 1, 1, 0, 1],

"cp": [
  1, 1, 1, 1, 1, 1, 1,
  1, 0, 0, 0, 0, 0, 0,
  1, 0, 1, 1, 1, 1, 0,
  1, 0, 1, 0, 0, 1, 0,
  1, 0, 1, 1, 1, 1, 1,
  1, 0, 0, 0, 0, 0, 0,
  1, 1, 1, 1, 1, 1, 1],

"df": [
  1, 0, 0, 1, 0, 0, 0,
  1, 0, 0, 1, 0, 0, 0,
  1, 1, 1, 1, 1, 1, 1,
  0, 0, 0, 0, 0, 0, 0,
  0, 1, 1, 1, 1, 1, 0,
  1, 0, 0, 0, 0, 0, 1,
  1, 1, 1, 1, 1, 1, 1],

"fi": [
  1, 0, 1, 0, 1, 1, 1,
  1, 0, 1, 0, 0, 1, 0,
  1, 0, 1, 0, 0, 1, 0,
  1, 0, 1, 0, 0, 1, 0,
  1, 0, 1, 0, 1, 1, 1,
  1, 0, 1, 0, 0, 0, 0,
  1, 1, 1, 1, 1, 1, 1],

"hd": [
  0, 1, 1, 1, 1, 1, 0,
  1, 0, 0, 0, 0, 0, 1,
  1, 1, 1, 1, 1, 1, 1,
  0, 0, 0, 0, 0, 0, 0,
  1, 1, 1, 1, 1, 1, 1,
  0, 0, 0, 1, 0, 0, 0,
  1, 1, 1, 1, 1, 1, 1],

"lk": [
  1, 0, 1, 0, 0, 0, 1,
  1, 0, 1, 0, 0, 1, 1,
  1, 0, 1, 1, 1, 0, 0,
  1, 0, 1, 0, 0, 1, 1,
  1, 0, 1, 0, 0, 0, 1,
  1, 0, 0, 0, 0, 0, 0,
  1, 1, 1, 1, 1, 1, 1],

"mc": [
  0, 0, 1, 1, 1, 1, 1,
  0, 0, 1, 0, 0, 0, 0,
  1, 1, 1, 0, 0, 0, 0,
  1, 0, 0, 1, 1, 1, 1,
  1, 0, 0, 1, 0, 0, 0,
  1, 0, 0, 1, 0, 0, 0,
  1, 0, 0, 1, 0, 0, 0],

"mm": [
  1, 1, 1, 1, 1, 0, 0,
  0, 0, 0, 0, 1, 0, 0,
  1, 1, 1, 0, 1, 1, 1,
  0, 0, 1, 0, 0, 0, 1,
  0, 0, 1, 1, 1, 0, 1,
  0, 0, 0, 0, 1, 0, 1,
  0, 0, 0, 0, 1, 0, 1],

"mm2": [
  1, 1, 1, 1, 1, 1, 1,
  1, 0, 0, 1, 0, 0, 1,
  1, 0, 0, 1, 0, 0, 1,
  0, 0, 0, 0, 0, 0, 0,
  1, 1, 1, 1, 1, 1, 1,
  1, 0, 0, 1, 0, 0, 1,
  1, 0, 0, 1, 0, 0, 1],

"obm": [
  1, 1, 1, 0, 1, 0, 0,
  1, 0, 1, 0, 1, 1, 1,
  1, 0, 1, 0, 1, 0, 1,
  1, 1, 1, 0, 1, 1, 1,
  0, 0, 0, 0, 0, 0, 0,
  1, 1, 1, 1, 1, 1, 1,
  1, 0, 0, 1, 0, 0, 1],

"ml": [
  1, 1, 1, 1, 0, 0, 0,
  0, 0, 0, 1, 0, 0, 0,
  0, 0, 0, 1, 0, 0, 0,
  1, 0, 0, 1, 1, 1, 1,
  1, 0, 0, 0, 0, 0, 1,
  1, 0, 0, 0, 0, 0, 1,
  1, 1, 1, 1, 0, 0, 1],

"of": [
  1, 1, 1, 1, 1, 1, 1,
  0, 0, 0, 0, 1, 0, 1,
  1, 1, 1, 0, 1, 0, 1,
  1, 0, 1, 0, 1, 0, 1,
  1, 0, 1, 0, 1, 0, 1,
  1, 0, 1, 0, 1, 0, 1,
  1, 1, 1, 0, 1, 0, 1],

"pr": [
  1, 1, 1, 1, 1, 1, 1,
  1, 0, 0, 0, 0, 0, 1,
  1, 1, 1, 1, 1, 1, 1,
  1, 0, 0, 0, 0, 0, 0,
  1, 0, 1, 1, 0, 1, 1,
  1, 0, 1, 0, 1, 0, 0,
  1, 0, 1, 1, 1, 1, 1],

"ps": [
  1, 1, 1, 0, 1, 1, 1,
  1, 0, 1, 0, 1, 0, 0,
  1, 0, 1, 0, 1, 1, 1,
  1, 0, 1, 0, 0, 0, 1,
  1, 0, 1, 0, 1, 1, 1,
  1, 0, 1, 0, 0, 0, 0,
  1, 1, 1, 1, 1, 1, 1],

"re": [
  1, 1, 1, 1, 1, 1, 1,
  1, 0, 0, 0, 0, 0, 0,
  1, 0, 1, 1, 1, 1, 1,
  1, 0, 1, 0, 0, 0, 0,
  1, 0, 1, 1, 1, 1, 1,
  1, 0, 1, 0, 0, 0, 0,
  1, 0, 1, 1, 1, 1, 1],

"sc": [
  1, 1, 1, 1, 1, 1, 1,
  1, 0, 0, 0, 0, 0, 0,
  1, 1, 1, 0, 1, 1, 1,
  0, 0, 1, 0, 1, 0, 0,
  0, 0, 1, 0, 1, 0, 0,
  0, 0, 1, 0, 1, 0, 0,
  1, 1, 1, 0, 1, 1, 1],

"sm": [
  1, 0, 0, 1, 1, 1, 1,
  1, 0, 0, 1, 0, 0, 1,
  1, 1, 1, 1, 0, 0, 1,
  0, 0, 0, 0, 0, 0, 0,
  1, 1, 1, 1, 1, 1, 1,
  1, 0, 0, 1, 0, 0, 1,
  1, 0, 0, 1, 0, 0, 1],

"sm2": [
  1, 1, 1, 1, 1, 0, 0,
  0, 0, 0, 0, 1, 0, 0,
  1, 1, 1, 0, 1, 1, 1,
  1, 0, 0, 0, 0, 0, 1,
  1, 1, 1, 1, 1, 0, 1,
  0, 0, 0, 0, 1, 0, 1,
  1, 1, 1, 1, 1, 0, 1],

"sn": [
  1, 1, 0, 1, 1, 1, 1,
  1, 0, 0, 1, 0, 0, 1,
  1, 0, 0, 1, 0, 0, 1,
  1, 0, 0, 0, 0, 0, 0,
  1, 1, 1, 1, 1, 1, 1,
  0, 0, 0, 0, 0, 0, 1,
  1, 1, 1, 1, 1, 1, 1],

"tm": [
  1, 1, 1, 1, 1, 0, 0,
  0, 0, 0, 0, 1, 0, 0,
  1, 0, 0, 0, 1, 1, 1,
  1, 0, 0, 0, 0, 0, 1,
  1, 1, 1, 1, 1, 0, 1,
  1, 0, 0, 0, 0, 0, 1,
  1, 0, 0, 0, 0, 0, 1],

"vc": [
  1, 0, 1, 0, 1, 1, 1,
  1, 0, 1, 0, 1, 0, 0,
  1, 0, 1, 0, 1, 0, 0,
  1, 0, 1, 0, 1, 0, 0,
  1, 0, 1, 0, 1, 0, 0,
  1, 0, 1, 0, 1, 0, 0,
  0, 1, 0, 0, 1, 1, 1],

"fb": [
  1, 1, 1, 1, 1, 1, 1,
  0, 0, 0, 0, 1, 0, 1,
  1, 0, 0, 0, 1, 0, 1,
  1, 1, 1, 0, 1, 0, 1,
  1, 0, 1, 0, 1, 0, 1,
  1, 0, 1, 0, 1, 0, 1,
  1, 1, 1, 0, 1, 0, 1],

"fb2": [
  1, 0, 1, 0, 1, 0, 0,
  1, 0, 1, 0, 1, 1, 1,
  1, 0, 1, 0, 1, 0, 1,
  1, 0, 1, 0, 1, 0, 1,
  1, 0, 1, 0, 1, 1, 1,
  1, 0, 1, 0, 0, 0, 0,
  1, 1, 1, 1, 1, 1, 1]
}
